typed_soup/__init__.py
typed_soup/typed_soup.py
typed_soup-1.0.0.dist-info/METADATA
typed_soup-1.0.0.dist-info/WHEEL
typed_soup-1.0.0.dist-info/RECORD
