Metadata-Version: 2.4
Name: typed-soup
Version: 1.0.0
Summary: A type-safe wrapper around BeautifulSoup and related HTML parsing utilities
License: MIT
Keywords: beautifulsoup,html,parsing,type-safe,type-hints,static-typing,mypy,pyright,web-scraping,html-parsing,xml-parsing
Author: Robert Shecter
Author-email: robert@public.law
Requires-Python: >=3.10
Classifier: Development Status :: 4 - Beta
Classifier: Intended Audience :: Developers
Classifier: License :: OSI Approved :: MIT License
Classifier: Programming Language :: Python :: 3
Classifier: Programming Language :: Python :: 3.10
Classifier: Programming Language :: Python :: 3.11
Classifier: Programming Language :: Python :: 3.12
Classifier: Programming Language :: Python :: 3.13
Classifier: Topic :: Software Development :: Libraries :: Python Modules
Classifier: Programming Language :: Python :: Implementation :: CPython
Classifier: Typing :: Typed
Classifier: Topic :: Text Processing :: Markup :: HTML
Classifier: Topic :: Software Development :: Quality Assurance
Requires-Dist: beautifulsoup4
Requires-Dist: toolz
Project-URL: Documentation, https://github.com/public-law/typed-soup#readme
Project-URL: Homepage, https://github.com/public-law/typed-soup
Project-URL: Issues, https://github.com/public-law/typed-soup/issues
Project-URL: Repository, https://github.com/public-law/typed-soup.git
